PeopleDetection/__init__.py
PeopleDetection/demo.py
PeopleDetection/detector.py
peodect-0.0.1.dist-info/METADATA
peodect-0.0.1.dist-info/WHEEL
peodect-0.0.1.dist-info/top_level.txt
peodect-0.0.1.dist-info/RECORD
